[
  {
    "name": "Veerle Deschepper",
    "title": "Creator",
    "company": "daktadeo.be",
    "projects": [
      {
        "label": "daktadeo/*",
        "url": "https://www.github.com/daktadeo"
      }
    ],
    "location": "Moscou, Gent, Belgium",
    "languages": ["Dutch", "English", "some bit of French & German"],
    "website": {
      "label": "gompje.be",
      "url": "https://gompje.be"
    },
    "socials": {
      "github": "gompje"
    },
    "sponsor": false
  },
  {
    "name": "Ann Deraedt",
    "title": "Lecturer",
    "company": "howest.be",
    "location": "Belgium",
    "languages": ["Dutch", "English"],
    "website": {
      "label": "deraedta.be",
      "url": "https://deraedta.be"
    },
    "socials": {
      "github": "deraedta"
    },
    "sponsor": false
  },
  {
    "name": "Arlette Acke",
    "title": "Quality Control",
    "company": "daktadeo.be",
    "location": "Belgium",
    "languages": ["Dutch", "English", "French", "German"],
    "socials": {
      "github": "LettekeA"
    },
    "sponsor": false
  },
  {
    "name": "Dries Ogenae",
    "title": "Consultant",
    "company": "dobs.be",
    "location": "Belgium",
    "languages": ["Dutch", "English"],
    "socials": {
      "github": "DriesOngenae"
    },
    "avatarPic": "https://ui-avatars.com/api/?background=random&name=Dries+Ogenae",
    "sponsor": false
  },
  {
    "name": "Britt Wittoek",
    "title": "Student",
    "location": "Belgium",
    "languages": ["Dutch", "English"],
    "socials": {
      "github": ""
    },
    "avatarPic": "https://ui-avatars.com/api/?background=random&name=Britt+Wittoek",
    "sponsor": false
  }
]
